ccdingtalk/__init__.py
ccdingtalk-0.1.dist-info/METADATA
ccdingtalk-0.1.dist-info/WHEEL
ccdingtalk-0.1.dist-info/top_level.txt
ccdingtalk-0.1.dist-info/RECORD
