Metadata-Version: 2.1
Name: ccdingtalk
Version: 0.1
Summary: Send dingtalk webhook with simple interface and load balance
Home-page: https://github.com/OpenFibers/CCDingTalk
Author: OpenFibers
Author-email: openfibers@gmail.com
License: MIT
Platform: UNKNOWN
